kiara_plugin/dev/__init__.py
kiara_plugin/dev/data_types.py
kiara_plugin/dev/defaults.py
kiara_plugin/dev/models.py
kiara_plugin/dev/py.typed
kiara_plugin/dev/version.txt
kiara_plugin/dev/interfaces/__init__.py
kiara_plugin/dev/interfaces/cli/__init__.py
kiara_plugin/dev/interfaces/cli/pkg_build.py
kiara_plugin/dev/modules/__init__.py
kiara_plugin/dev/pipelines/.gitkeep
kiara_plugin/dev/pipelines/__init__.py
kiara_plugin/dev/pkg_build/__init__.py
kiara_plugin/dev/pkg_build/models.py
kiara_plugin/dev/pkg_build/states.py
kiara_plugin/dev/pkg_build/conda/__init__.py
kiara_plugin/dev/pkg_build/conda/states.py
kiara_plugin/dev/pkg_build/rattler/__init__.py
kiara_plugin/dev/pkg_build/rattler/models.py
kiara_plugin/dev/pkg_build/rattler/states.py
kiara_plugin/dev/resources/.gitkeep
kiara_plugin/dev/resources/templates/meta.yaml.j2
kiara_plugin/dev/resources/templates/rattler-build-recipe.yaml.j2
kiara_plugin/dev/resources/templates/recipe.yaml.j2
kiara_plugin/dev/utils/__init__.py
kiara_plugin/dev/utils/pkg_utils.py
kiara_plugin_dev-0.2.0.dist-info/METADATA
kiara_plugin_dev-0.2.0.dist-info/WHEEL
kiara_plugin_dev-0.2.0.dist-info/entry_points.txt
kiara_plugin_dev-0.2.0.dist-info/licenses/LICENSE
kiara_plugin_dev-0.2.0.dist-info/RECORD
