Metadata-Version: 2.4
Name: kiara_plugin.dev
Version: 0.2.0
Summary: A kiara plugin to help with development related tasks (modules, pipelines, widgets,...).
Project-URL: homepage, https://github.com/DHARPA-Project/kiara_plugin.dev
Project-URL: documentation, https://DHARPA-Project.github.io/kiara_plugin.dev
Project-URL: repository, https://github.com/DHARPA-Project/kiara_plugin.dev
Author-email: Markus Binsteiner <markus@frkl.dev>
License: MPL-2.0
License-File: LICENSE
Keywords: kiara,kiara-plugin
Classifier: Development Status :: 3 - Alpha
Classifier: License :: OSI Approved :: Mozilla Public License 2.0 (MPL 2.0)
Classifier: Programming Language :: Python
Classifier: Programming Language :: Python :: 3
Classifier: Programming Language :: Python :: 3 :: Only
Classifier: Programming Language :: Python :: 3.9
Classifier: Programming Language :: Python :: 3.10
Classifier: Programming Language :: Python :: 3.11
Classifier: Programming Language :: Python :: 3.12
Classifier: Programming Language :: Python :: 3.13
Requires-Python: >=3.9
Requires-Dist: build>=1.2.2.post1
Requires-Dist: diskcache>=5.6.3
Requires-Dist: kiara-plugin-core-types<0.6.0,>=0.5.2
Requires-Dist: kiara<0.6.0,>=0.5.15
Requires-Dist: license-expression>=30.4.3
Provides-Extra: jupyter
Requires-Dist: kiara[jupyter]; extra == 'jupyter'
Provides-Extra: marimo
Requires-Dist: kiara[marimo]; extra == 'marimo'
